service_response/__init__.py
service_response/service_response.py
service_response-0.1.2.dist-info/LICENSE
service_response-0.1.2.dist-info/METADATA
service_response-0.1.2.dist-info/WHEEL
service_response-0.1.2.dist-info/top_level.txt
service_response-0.1.2.dist-info/RECORD
