Metadata-Version: 2.2
Name: service_response
Version: 0.1.2
Summary: A library for managing git repositories in a directory.
Home-page: https://github.com/Armen-Jean-Andreasian/ServiceResponse
Author: Armen-Jean Andreasian
Author-email: armen_andreasian@proton.me
License: Custom License
Classifier: Programming Language :: Python :: 3
Classifier: License :: Other/Proprietary License
Classifier: Operating System :: OS Independent
Requires-Python: >=3.6
License-File: LICENSE
Dynamic: author
Dynamic: author-email
Dynamic: classifier
Dynamic: description
Dynamic: description-content-type
Dynamic: home-page
Dynamic: license
Dynamic: requires-python
Dynamic: summary
